pymultith/__init__.py
pymultith/dontyouwantme.txt
pymultith/pymultith.py
pymultith-1.0.0.dist-info/licenses/LICENSE
pymultith-1.0.0.dist-info/WHEEL
pymultith-1.0.0.dist-info/METADATA
pymultith-1.0.0.dist-info/RECORD
