Metadata-Version: 2.4
Name: pymultith
Version: 1.0.0
Summary: Simple Multi-Threading module, cuz python so slow :)
Author-email: Aymen MW <aymenmw@proton.me>
License-Expression: MIT
License-File: LICENSE
